[{"alternatives": [{"words": [{"startTime": "1.920s", "endTime": "2.160s", "word": "добрый", "confidence": 1}, {"startTime": "2.180s", "endTime": "2.400s", "word": "вечер", "confidence": 1}, {"startTime": "2.440s", "endTime": "2.560s", "word": "меня", "confidence": 1}, {"startTime": "2.600s", "endTime": "2.740s", "word": "зовут", "confidence": 1}, {"startTime": "2.780s", "endTime": "3.020s", "word": "андрей", "confidence": 1}, {"startTime": "3.080s", "endTime": "3.360s", "word": "слушаю", "confidence": 1}, {"startTime": "3.420s", "endTime": "4.160s", "word": "вас", "confidence": 1}], "text": "Добрый вечер меня зовут андрей слушаю вас", "confidence": 1}], "channelTag": "1"}, {"alternatives": [{"words": [{"startTime": "6.290s", "endTime": "7.070s", "word": "алло", "confidence": 1}], "text": "Алло", "confidence": 1}], "channelTag": "1"}, {"alternatives": [{"words": [{"startTime": "7.340s", "endTime": "7.680s", "word": "слушаю", "confidence": 1}, {"startTime": "7.740s", "endTime": "8.500s", "word": "вас", "confidence": 1}], "text": "Слушаю вас", "confidence": 1}], "channelTag": "1"}, {"alternatives": [{"words": [{"startTime": "9.240s", "endTime": "10.140s", "word": "здравствуйте", "confidence": 1}], "text": "Здравствуйте", "confidence": 1}], "channelTag": "1"}, {"alternatives": [{"words": [{"startTime": "11.420s", "endTime": "11.540s", "word": "ну", "confidence": 1}, {"startTime": "11.600s", "endTime": "11.940s", "word": "хочу", "confidence": 1}, {"startTime": "11.980s", "endTime": "12.240s", "word": "писить", "confidence": 1}, {"startTime": "12.280s", "endTime": "12.520s", "word": "сорок", "confidence": 1}, {"startTime": "12.560s", "endTime": "13.120s", "word": "восемь", "confidence": 1}, {"startTime": "13.200s", "endTime": "13.400s", "word": "десять", "confidence": 1}, {"startTime": "13.440s", "endTime": "13.700s", "word": "сорок", "confidence": 1}, {"startTime": "13.740s", "endTime": "14.180s", "word": "восемь", "confidence": 1}, {"startTime": "14.300s", "endTime": "14.600s", "word": "а", "confidence": 1}, {"startTime": "14.660s", "endTime": "15.600s", "word": "фамилия", "confidence": 1}], "text": "Ну хочу писить 48 10 48 а фамилия", "confidence": 1}], "channelTag": "1"}, {"alternatives": [{"words": [{"startTime": "16.100s", "endTime": "16.360s", "word": "почему", "confidence": 1}, {"startTime": "16.420s", "endTime": "17.020s", "word": "ты", "confidence": 1}], "text": "Почему ты", "confidence": 1}], "channelTag": "1"}, {"alternatives": [{"words": [{"startTime": "17.940s", "endTime": "18.580s", "word": "десять", "confidence": 1}], "text": "10", "confidence": 1}], "channelTag": "1"}, {"alternatives": [{"words": [{"startTime": "19.770s", "endTime": "20.950s", "word": "а", "confidence": 1}], "text": "А", "confidence": 1}], "channelTag": "1"}, {"alternatives": [{"words": [{"startTime": "21.540s", "endTime": "21.640s", "word": "ну", "confidence": 1}, {"startTime": "21.680s", "endTime": "21.940s", "word": "короче", "confidence": 1}, {"startTime": "22s", "endTime": "23.960s", "word": "говоря", "confidence": 1}], "text": "Ну короче говоря", "confidence": 1}], "channelTag": "1"}, {"alternatives": [{"words": [{"startTime": "24.990s", "endTime": "25.090s", "word": "не", "confidence": 1}, {"startTime": "25.210s", "endTime": "26.290s", "word": "данил", "confidence": 1}], "text": "Не данил", "confidence": 1}], "channelTag": "1"}, {"alternatives": [{"words": [{"startTime": "27.890s", "endTime": "28.570s", "word": "ни", "confidence": 1}, {"startTime": "28.630s", "endTime": "28.870s", "word": "первый", "confidence": 1}, {"startTime": "28.890s", "endTime": "28.970s", "word": "ни", "confidence": 1}, {"startTime": "29.010s", "endTime": "29.290s", "word": "второй", "confidence": 1}, {"startTime": "29.330s", "endTime": "29.450s", "word": "ни", "confidence": 1}, {"startTime": "29.490s", "endTime": "30.230s", "word": "третий", "confidence": 1}], "text": "Ни 1 ни 2 ни 3", "confidence": 1}], "channelTag": "1"}, {"alternatives": [{"words": [{"startTime": "31.070s", "endTime": "31.290s", "word": "через", "confidence": 1}, {"startTime": "31.330s", "endTime": "33.730s", "word": "приставку", "confidence": 1}], "text": "Через приставку", "confidence": 1}], "channelTag": "1"}, {"alternatives": [{"words": [{"startTime": "34.660s", "endTime": "35.720s", "word": "а", "confidence": 1}], "text": "А", "confidence": 1}], "channelTag": "1"}, {"alternatives": [{"words": [{"startTime": "35.690s", "endTime": "35.970s", "word": "просто", "confidence": 1}, {"startTime": "36.030s", "endTime": "36.450s", "word": "зависла", "confidence": 1}, {"startTime": "36.490s", "endTime": "37.530s", "word": "все", "confidence": 1}], "text": "Просто зависла все", "confidence": 1}], "channelTag": "1"}, {"alternatives": [{"words": [{"startTime": "38.830s", "endTime": "39.270s", "word": "выключите", "confidence": 1}, {"startTime": "39.310s", "endTime": "39.670s", "word": "пожалуйста", "confidence": 1}, {"startTime": "39.730s", "endTime": "40.130s", "word": "доставку", "confidence": 1}, {"startTime": "40.190s", "endTime": "40.650s", "word": "зарядки", "confidence": 1}, {"startTime": "40.750s", "endTime": "40.890s", "word": "на", "confidence": 1}, {"startTime": "40.910s", "endTime": "41.950s", "word": "включите", "confidence": 1}], "text": "Выключите пожалуйста доставку зарядки на включите", "confidence": 1}], "channelTag": "1"}, {"alternatives": [{"words": [{"startTime": "43.560s", "endTime": "43.720s", "word": "так", "confidence": 1}, {"startTime": "43.780s", "endTime": "43.860s", "word": "а", "confidence": 1}, {"startTime": "43.940s", "endTime": "44.740s", "word": "другие", "confidence": 1}, {"startTime": "44.760s", "endTime": "44.940s", "word": "сейчас", "confidence": 1}, {"startTime": "45.120s", "endTime": "45.240s", "word": "я", "confidence": 1}, {"startTime": "45.300s", "endTime": "45.600s", "word": "зашел", "confidence": 1}, {"startTime": "45.680s", "endTime": "45.720s", "word": "я", "confidence": 1}, {"startTime": "45.740s", "endTime": "45.860s", "word": "имею", "confidence": 1}, {"startTime": "45.880s", "endTime": "46.140s", "word": "ввиду", "confidence": 1}, {"startTime": "46.180s", "endTime": "47.140s", "word": "вот", "confidence": 1}], "text": "Так а другие сейчас я зашел я имею ввиду вот", "confidence": 1}], "channelTag": "1"}, {"alternatives": [{"words": [{"startTime": "47.450s", "endTime": "47.750s", "word": "какой", "confidence": 1}, {"startTime": "47.790s", "endTime": "48.090s", "word": "канал", "confidence": 1}, {"startTime": "48.130s", "endTime": "48.930s", "word": "там", "confidence": 1}], "text": "Какой канал там", "confidence": 1}], "channelTag": "1"}, {"alternatives": [{"words": [{"startTime": "48.890s", "endTime": "50.290s", "word": "а", "confidence": 1}], "text": "А", "confidence": 1}], "channelTag": "1"}, {"alternatives": [{"words": [{"startTime": "52.120s", "endTime": "52.720s", "word": "да", "confidence": 1}], "text": "Да", "confidence": 1}], "channelTag": "1"}, {"alternatives": [{"words": [{"startTime": "55.030s", "endTime": "56.490s", "word": "белоруссия", "confidence": 1}], "text": "Белоруссия", "confidence": 1}], "channelTag": "1"}, {"alternatives": [{"words": [{"startTime": "56.790s", "endTime": "57.010s", "word": "новый", "confidence": 1}, {"startTime": "57.050s", "endTime": "57.210s", "word": "год", "confidence": 1}, {"startTime": "57.250s", "endTime": "58.410s", "word": "показывает", "confidence": 1}], "text": "Новый год показывает", "confidence": 1}], "channelTag": "1"}, {"alternatives": [{"words": [{"startTime": "60.210s", "endTime": "60.610s", "word": "выключите", "confidence": 1}, {"startTime": "60.650s", "endTime": "60.950s", "word": "пожалуйста", "confidence": 1}, {"startTime": "61.850s", "endTime": "61.890s", "word": "и", "confidence": 1}, {"startTime": "61.970s", "endTime": "62.210s", "word": "снова", "confidence": 1}, {"startTime": "62.230s", "endTime": "62.910s", "word": "включите", "confidence": 1}], "text": "Выключите пожалуйста и снова включите", "confidence": 1}], "channelTag": "1"}, {"alternatives": [{"words": [{"startTime": "69.880s", "endTime": "70.240s", "word": "яндекс", "confidence": 1}, {"startTime": "70.300s", "endTime": "71.220s", "word": "такси", "confidence": 1}], "text": "Яндекс такси", "confidence": 1}], "channelTag": "1"}, {"alternatives": [{"words": [{"startTime": "80.660s", "endTime": "80.780s", "word": "ну", "confidence": 1}, {"startTime": "80.820s", "endTime": "81.920s", "word": "включи", "confidence": 1}], "text": "Ну включи", "confidence": 1}], "channelTag": "1"}, {"alternatives": [{"words": [{"startTime": "83.750s", "endTime": "84.630s", "word": "ток", "confidence": 1}], "text": "Ток", "confidence": 1}], "channelTag": "1"}, {"alternatives": [{"words": [{"startTime": "84.950s", "endTime": "85.110s", "word": "дом", "confidence": 1}, {"startTime": "85.150s", "endTime": "85.310s", "word": "два", "confidence": 1}, {"startTime": "85.370s", "endTime": "85.910s", "word": "показывает", "confidence": 1}, {"startTime": "85.990s", "endTime": "86.390s", "word": "просто", "confidence": 1}, {"startTime": "86.470s", "endTime": "87.450s", "word": "надо", "confidence": 1}], "text": "Дом 2 показывает просто надо", "confidence": 1}], "channelTag": "1"}, {"alternatives": [{"words": [{"startTime": "88.690s", "endTime": "89.310s", "word": "а", "confidence": 1}], "text": "А", "confidence": 1}], "channelTag": "1"}, {"alternatives": [{"words": [{"startTime": "91.370s", "endTime": "91.690s", "word": "когда", "confidence": 1}, {"startTime": "91.770s", "endTime": "92.030s", "word": "вы", "confidence": 1}, {"startTime": "92.090s", "endTime": "92.670s", "word": "предупреждаете", "confidence": 1}, {"startTime": "92.710s", "endTime": "93.170s", "word": "приставку", "confidence": 1}, {"startTime": "93.230s", "endTime": "93.350s", "word": "там", "confidence": 1}, {"startTime": "93.410s", "endTime": "94.070s", "word": "сначала", "confidence": 1}, {"startTime": "94.110s", "endTime": "94.350s", "word": "должна", "confidence": 1}, {"startTime": "94.390s", "endTime": "94.730s", "word": "была", "confidence": 1}, {"startTime": "94.830s", "endTime": "95.150s", "word": "карта", "confidence": 1}, {"startTime": "95.210s", "endTime": "95.970s", "word": "меню", "confidence": 1}], "text": "Когда вы предупреждаете приставку там сначала должна была карта меню", "confidence": 1}], "channelTag": "1"}, {"alternatives": [{"words": [{"startTime": "97.140s", "endTime": "97.220s", "word": "вы", "confidence": 1}, {"startTime": "97.260s", "endTime": "97.820s", "word": "знаете", "confidence": 1}, {"startTime": "97.860s", "endTime": "99.340s", "word": "все", "confidence": 1}], "text": "Вы знаете все", "confidence": 1}], "channelTag": "1"}, {"alternatives": [{"words": [{"startTime": "99.670s", "endTime": "99.930s", "word": "после", "confidence": 1}, {"startTime": "99.990s", "endTime": "100.490s", "word": "последнего", "confidence": 1}, {"startTime": "100.550s", "endTime": "100.930s", "word": "мастера", "confidence": 1}, {"startTime": "100.970s", "endTime": "101.210s", "word": "почему", "confidence": 1}, {"startTime": "101.270s", "endTime": "101.350s", "word": "то", "confidence": 1}, {"startTime": "101.510s", "endTime": "102.290s", "word": "это", "confidence": 1}], "text": "После последнего мастера почему то это", "confidence": 1}], "channelTag": "1"}, {"alternatives": [{"words": [{"startTime": "102.450s", "endTime": "102.950s", "word": "приставка", "confidence": 1}, {"startTime": "103.010s", "endTime": "103.790s", "word": "перезагружалась", "confidence": 1}, {"startTime": "103.850s", "endTime": "104.150s", "word": "кнопка", "confidence": 1}, {"startTime": "104.210s", "endTime": "104.430s", "word": "теперь", "confidence": 1}, {"startTime": "104.450s", "endTime": "104.530s", "word": "вы", "confidence": 1}, {"startTime": "104.550s", "endTime": "105.610s", "word": "включает", "confidence": 1}], "text": "Приставка перезагружалась кнопка теперь вы включает", "confidence": 1}], "channelTag": "1"}, {"alternatives": [{"words": [{"startTime": "107.570s", "endTime": "109.230s", "word": "да", "confidence": 1}], "text": "Да", "confidence": 1}], "channelTag": "1"}, {"alternatives": [{"words": [{"startTime": "109.950s", "endTime": "111.610s", "word": "пока", "confidence": 1}], "text": "Пока", "confidence": 1}], "channelTag": "1"}, {"alternatives": [{"words": [{"startTime": "113.860s", "endTime": "113.960s", "word": "не", "confidence": 1}, {"startTime": "114s", "endTime": "114.740s", "word": "понял", "confidence": 1}], "text": "Не понял", "confidence": 1}], "channelTag": "1"}, {"alternatives": [{"words": [{"startTime": "115.940s", "endTime": "117.040s", "word": "ну", "confidence": 1}, {"startTime": "117.100s", "endTime": "117.240s", "word": "как", "confidence": 1}, {"startTime": "117.260s", "endTime": "117.420s", "word": "вот", "confidence": 1}, {"startTime": "117.500s", "endTime": "117.660s", "word": "меня", "confidence": 1}, {"startTime": "117.700s", "endTime": "117.800s", "word": "на", "confidence": 1}, {"startTime": "117.860s", "endTime": "118.220s", "word": "пути", "confidence": 1}, {"startTime": "118.340s", "endTime": "118.660s", "word": "разве", "confidence": 1}, {"startTime": "118.700s", "endTime": "119.520s", "word": "кнопки", "confidence": 1}], "text": "Ну как вот меня на пути разве кнопки", "confidence": 1}], "channelTag": "1"}, {"alternatives": [{"words": [{"startTime": "119.530s", "endTime": "119.730s", "word": "она", "confidence": 1}, {"startTime": "119.770s", "endTime": "119.870s", "word": "бы", "confidence": 1}, {"startTime": "119.910s", "endTime": "120.350s", "word": "телевизора", "confidence": 1}, {"startTime": "120.390s", "endTime": "120.610s", "word": "одно", "confidence": 1}, {"startTime": "120.670s", "endTime": "120.790s", "word": "на", "confidence": 1}, {"startTime": "120.830s", "endTime": "121.730s", "word": "доставки", "confidence": 1}], "text": "Она бы телевизора 1 на доставки", "confidence": 1}], "channelTag": "1"}, {"alternatives": [{"words": [{"startTime": "125.210s", "endTime": "126.050s", "word": "ну", "confidence": 1}], "text": "Ну", "confidence": 1}], "channelTag": "1"}, {"alternatives": [{"words": [{"startTime": "126.260s", "endTime": "126.360s", "word": "на", "confidence": 1}, {"startTime": "126.400s", "endTime": "127.360s", "word": "одну", "confidence": 1}], "text": "На 1", "confidence": 1}], "channelTag": "1"}, {"alternatives": [{"words": [{"startTime": "128.410s", "endTime": "128.630s", "word": "а", "confidence": 1}, {"startTime": "128.690s", "endTime": "128.790s", "word": "то", "confidence": 1}, {"startTime": "128.830s", "endTime": "129.050s", "word": "было", "confidence": 1}, {"startTime": "129.090s", "endTime": "129.230s", "word": "что", "confidence": 1}, {"startTime": "129.770s", "endTime": "131.330s", "word": "перезагрузка", "confidence": 1}], "text": "А то было что перезагрузка", "confidence": 1}], "channelTag": "1"}, {"alternatives": [{"words": [{"startTime": "131.970s", "endTime": "132.670s", "word": "да", "confidence": 1}], "text": "Да", "confidence": 1}], "channelTag": "1"}, {"alternatives": [{"words": [{"startTime": "132.640s", "endTime": "132.700s", "word": "а", "confidence": 1}, {"startTime": "132.760s", "endTime": "133.060s", "word": "причем", "confidence": 1}, {"startTime": "133.100s", "endTime": "133.720s", "word": "здесь", "confidence": 1}, {"startTime": "133.780s", "endTime": "133.820s", "word": "я", "confidence": 1}, {"startTime": "133.860s", "endTime": "134.260s", "word": "попросил", "confidence": 1}, {"startTime": "134.300s", "endTime": "134.660s", "word": "выключить", "confidence": 1}, {"startTime": "134.700s", "endTime": "135.240s", "word": "приставку", "confidence": 1}, {"startTime": "135.340s", "endTime": "135.500s", "word": "из", "confidence": 1}, {"startTime": "135.580s", "endTime": "137.020s", "word": "розетки", "confidence": 1}], "text": "А причем здесь я попросил выключить приставку из розетки", "confidence": 1}], "channelTag": "1"}, {"alternatives": [{"words": [{"startTime": "136.960s", "endTime": "137.080s", "word": "я", "confidence": 1}, {"startTime": "137.140s", "endTime": "137.360s", "word": "уже", "confidence": 1}, {"startTime": "137.440s", "endTime": "137.960s", "word": "выключил", "confidence": 1}, {"startTime": "138.060s", "endTime": "138.800s", "word": "ножики", "confidence": 1}, {"startTime": "138.840s", "endTime": "139.260s", "word": "включи", "confidence": 1}, {"startTime": "139.340s", "endTime": "140.260s", "word": "оно", "confidence": 1}], "text": "Я уже выключил ножики включи оно", "confidence": 1}], "channelTag": "1"}, {"alternatives": [{"words": [{"startTime": "141.150s", "endTime": "142.630s", "word": "просто", "confidence": 1}], "text": "Просто", "confidence": 1}], "channelTag": "1"}, {"alternatives": [{"words": [{"startTime": "142.580s", "endTime": "142.960s", "word": "черно", "confidence": 1}, {"startTime": "143s", "endTime": "144.560s", "word": "тарелки", "confidence": 1}], "text": "Черно тарелки", "confidence": 1}], "channelTag": "1"}, {"alternatives": [{"words": [{"startTime": "145.060s", "endTime": "145.160s", "word": "но", "confidence": 1}, {"startTime": "145.200s", "endTime": "145.320s", "word": "она", "confidence": 1}, {"startTime": "145.360s", "endTime": "145.440s", "word": "не", "confidence": 1}, {"startTime": "145.480s", "endTime": "145.720s", "word": "сразу", "confidence": 1}, {"startTime": "145.760s", "endTime": "146.200s", "word": "загрузиться", "confidence": 1}, {"startTime": "146.240s", "endTime": "146.540s", "word": "немного", "confidence": 1}, {"startTime": "146.600s", "endTime": "147.820s", "word": "подтвердите", "confidence": 1}], "text": "Но она не сразу загрузиться немного подтвердите", "confidence": 1}], "channelTag": "1"}, {"alternatives": [{"words": [{"startTime": "149.470s", "endTime": "149.650s", "word": "то", "confidence": 1}, {"startTime": "149.690s", "endTime": "150.230s", "word": "загружается", "confidence": 1}, {"startTime": "150.250s", "endTime": "150.550s", "word": "старт", "confidence": 1}, {"startTime": "150.570s", "endTime": "151.230s", "word": "поменяет", "confidence": 1}, {"startTime": "151.290s", "endTime": "151.550s", "word": "оттуда", "confidence": 1}, {"startTime": "151.610s", "endTime": "151.750s", "word": "уже", "confidence": 1}, {"startTime": "151.810s", "endTime": "152.250s", "word": "приходите", "confidence": 1}, {"startTime": "152.290s", "endTime": "152.330s", "word": "к", "confidence": 1}, {"startTime": "152.350s", "endTime": "152.810s", "word": "просмотру", "confidence": 1}, {"startTime": "152.910s", "endTime": "154.170s", "word": "телевидения", "confidence": 1}], "text": "То загружается старт поменяет оттуда уже приходите к просмотру телевидения", "confidence": 1}], "channelTag": "1"}, {"alternatives": [{"words": [{"startTime": "158.700s", "endTime": "159.660s", "word": "а", "confidence": 1}], "text": "А", "confidence": 1}], "channelTag": "1"}, {"alternatives": [{"words": [{"startTime": "162.610s", "endTime": "162.970s", "word": "сейчас", "confidence": 1}, {"startTime": "163.030s", "endTime": "164.050s", "word": "попробую", "confidence": 1}], "text": "Сейчас попробую", "confidence": 1}], "channelTag": "1"}, {"alternatives": [{"words": [{"startTime": "181.160s", "endTime": "193.800s", "word": "а", "confidence": 1}], "text": "А", "confidence": 1}], "channelTag": "1"}, {"alternatives": [{"words": [{"startTime": "213.490s", "endTime": "214.190s", "word": "да", "confidence": 1}], "text": "Да", "confidence": 1}], "channelTag": "1"}, {"alternatives": [{"words": [{"startTime": "222.010s", "endTime": "222.070s", "word": "то", "confidence": 1}, {"startTime": "222.110s", "endTime": "222.230s", "word": "есть", "confidence": 1}, {"startTime": "222.270s", "endTime": "222.410s", "word": "так", "confidence": 1}, {"startTime": "222.430s", "endTime": "222.470s", "word": "и", "confidence": 1}, {"startTime": "222.510s", "endTime": "222.590s", "word": "не", "confidence": 1}, {"startTime": "222.630s", "endTime": "223.130s", "word": "работают", "confidence": 1}, {"startTime": "223.370s", "endTime": "225.770s", "word": "каналы", "confidence": 1}], "text": "То есть так и не работают каналы", "confidence": 1}], "channelTag": "1"}, {"alternatives": [{"words": [{"startTime": "226.010s", "endTime": "226.090s", "word": "не", "confidence": 1}, {"startTime": "226.130s", "endTime": "226.570s", "word": "работал", "confidence": 1}, {"startTime": "226.690s", "endTime": "226.770s", "word": "и", "confidence": 1}, {"startTime": "226.810s", "endTime": "227.550s", "word": "будет", "confidence": 1}], "text": "Не работал и будет", "confidence": 1}], "channelTag": "1"}, {"alternatives": [{"words": [{"startTime": "227.720s", "endTime": "228.020s", "word": "русские", "confidence": 1}, {"startTime": "228.060s", "endTime": "229s", "word": "программы", "confidence": 1}], "text": "Русские программы", "confidence": 1}], "channelTag": "1"}, {"alternatives": [{"words": [{"startTime": "233.620s", "endTime": "234.920s", "word": "да", "confidence": 1}], "text": "Да", "confidence": 1}], "channelTag": "1"}, {"alternatives": [{"words": [{"startTime": "235.700s", "endTime": "235.880s", "word": "все", "confidence": 1}, {"startTime": "235.920s", "endTime": "237.280s", "word": "также", "confidence": 1}], "text": "Все также", "confidence": 1}], "channelTag": "1"}, {"alternatives": [{"words": [{"startTime": "237.880s", "endTime": "238.100s", "word": "можно", "confidence": 1}, {"startTime": "238.140s", "endTime": "238.340s", "word": "тогда", "confidence": 1}, {"startTime": "238.380s", "endTime": "238.680s", "word": "сделать", "confidence": 1}, {"startTime": "238.780s", "endTime": "239s", "word": "просто", "confidence": 1}, {"startTime": "239.040s", "endTime": "240.160s", "word": "настроек", "confidence": 1}, {"startTime": "240.200s", "endTime": "240.320s", "word": "для", "confidence": 1}, {"startTime": "240.360s", "endTime": "240.540s", "word": "этого", "confidence": 1}, {"startTime": "240.600s", "endTime": "240.900s", "word": "зайдите", "confidence": 1}, {"startTime": "240.940s", "endTime": "241.280s", "word": "пожалуйста", "confidence": 1}, {"startTime": "241.680s", "endTime": "241.820s", "word": "мне", "confidence": 1}, {"startTime": "241.860s", "endTime": "242.400s", "word": "приставки", "confidence": 1}, {"startTime": "242.520s", "endTime": "242.820s", "word": "пункт", "confidence": 1}, {"startTime": "242.880s", "endTime": "243.960s", "word": "еще", "confidence": 1}], "text": "Можно тогда сделать просто настроек для этого зайдите пожалуйста мне приставки пункт еще", "confidence": 1}], "channelTag": "1"}, {"alternatives": [{"words": [{"startTime": "259.800s", "endTime": "260.640s", "word": "угу", "confidence": 1}], "text": "Угу", "confidence": 1}], "channelTag": "1"}, {"alternatives": [{"words": [{"startTime": "260.930s", "endTime": "261.770s", "word": "настройка", "confidence": 1}, {"startTime": "261.830s", "endTime": "262.630s", "word": "настройки", "confidence": 1}, {"startTime": "262.690s", "endTime": "263.330s", "word": "охраняющие", "confidence": 1}, {"startTime": "263.510s", "endTime": "264.330s", "word": "рос", "confidence": 1}], "text": "Настройка настройки охраняющие рос", "confidence": 1}], "channelTag": "1"}, {"alternatives": [{"words": [{"startTime": "271.090s", "endTime": "271.930s", "word": "угу", "confidence": 1}], "text": "Угу", "confidence": 1}], "channelTag": "1"}, {"alternatives": [{"words": [{"startTime": "271.950s", "endTime": "272.270s", "word": "русский", "confidence": 1}, {"startTime": "272.710s", "endTime": "273.150s", "word": "заводские", "confidence": 1}, {"startTime": "273.190s", "endTime": "273.650s", "word": "настройки", "confidence": 1}, {"startTime": "273.710s", "endTime": "273.870s", "word": "еще", "confidence": 1}, {"startTime": "273.910s", "endTime": "274.090s", "word": "раз", "confidence": 1}, {"startTime": "274.110s", "endTime": "274.250s", "word": "вот", "confidence": 1}, {"startTime": "274.290s", "endTime": "274.410s", "word": "все", "confidence": 1}, {"startTime": "274.450s", "endTime": "274.910s", "word": "настройки", "confidence": 1}, {"startTime": "274.950s", "endTime": "274.990s", "word": "и", "confidence": 1}, {"startTime": "275.050s", "endTime": "275.410s", "word": "удалить", "confidence": 1}, {"startTime": "275.470s", "endTime": "276.310s", "word": "все", "confidence": 1}], "text": "Русский заводские настройки еще раз вот все настройки и удалить все", "confidence": 1}], "channelTag": "1"}, {"alternatives": [{"words": [{"startTime": "282.320s", "endTime": "284.120s", "word": "алиса", "confidence": 1}], "text": "Алиса", "confidence": 1}], "channelTag": "1"}, {"alternatives": [{"words": [{"startTime": "287.910s", "endTime": "288.170s", "word": "после", "confidence": 1}, {"startTime": "288.210s", "endTime": "288.390s", "word": "этого", "confidence": 1}, {"startTime": "288.430s", "endTime": "288.890s", "word": "приставка", "confidence": 1}, {"startTime": "288.930s", "endTime": "289.730s", "word": "перезагружается", "confidence": 1}, {"startTime": "289.830s", "endTime": "290.030s", "word": "там", "confidence": 1}, {"startTime": "290.070s", "endTime": "290.270s", "word": "будет", "confidence": 1}, {"startTime": "290.310s", "endTime": "290.690s", "word": "надпись", "confidence": 1}, {"startTime": "290.730s", "endTime": "290.870s", "word": "это", "confidence": 1}, {"startTime": "290.930s", "endTime": "291.330s", "word": "аварийная", "confidence": 1}, {"startTime": "291.370s", "endTime": "292.010s", "word": "перезагрузка", "confidence": 1}, {"startTime": "292.070s", "endTime": "293.370s", "word": "обновляется", "confidence": 1}], "text": "После этого приставка перезагружается там будет надпись это аварийная перезагрузка обновляется", "confidence": 1}], "channelTag": "1"}, {"alternatives": [{"words": [{"startTime": "293.500s", "endTime": "293.700s", "word": "можно", "confidence": 1}, {"startTime": "293.760s", "endTime": "294.040s", "word": "занять", "confidence": 1}, {"startTime": "294.100s", "endTime": "294.340s", "word": "около", "confidence": 1}, {"startTime": "294.400s", "endTime": "294.600s", "word": "пяти", "confidence": 1}, {"startTime": "294.660s", "endTime": "295.460s", "word": "минут", "confidence": 1}], "text": "Можно занять около 5 минут", "confidence": 1}], "channelTag": "1"}, {"alternatives": [{"words": [{"startTime": "295.600s", "endTime": "295.720s", "word": "до", "confidence": 1}, {"startTime": "295.720s", "endTime": "295.840s", "word": "до", "confidence": 1}, {"startTime": "295.900s", "endTime": "296.220s", "word": "десяти", "confidence": 1}, {"startTime": "296.280s", "endTime": "297.180s", "word": "минут", "confidence": 1}], "text": "До до 10 минут", "confidence": 1}], "channelTag": "1"}, {"alternatives": [{"words": [{"startTime": "297.500s", "endTime": "298.040s", "word": "ип", "confidence": 1}, {"startTime": "298.080s", "endTime": "298.320s", "word": "должно", "confidence": 1}, {"startTime": "298.380s", "endTime": "299.440s", "word": "заработать", "confidence": 1}], "text": "Ип должно заработать", "confidence": 1}], "channelTag": "1"}, {"alternatives": [{"words": [{"startTime": "300.440s", "endTime": "300.740s", "word": "если", "confidence": 1}, {"startTime": "300.840s", "endTime": "300.920s", "word": "не", "confidence": 1}, {"startTime": "300.980s", "endTime": "301.400s", "word": "поможет", "confidence": 1}, {"startTime": "301.440s", "endTime": "301.860s", "word": "позвонить", "confidence": 1}, {"startTime": "301.920s", "endTime": "302.100s", "word": "уже", "confidence": 1}, {"startTime": "302.160s", "endTime": "302.420s", "word": "завтра", "confidence": 1}, {"startTime": "302.460s", "endTime": "302.660s", "word": "потому", "confidence": 1}, {"startTime": "302.700s", "endTime": "302.780s", "word": "что", "confidence": 1}, {"startTime": "302.820s", "endTime": "303.020s", "word": "сейчас", "confidence": 1}, {"startTime": "303.100s", "endTime": "303.660s", "word": "техподдержка", "confidence": 1}, {"startTime": "303.720s", "endTime": "303.800s", "word": "не", "confidence": 1}, {"startTime": "303.840s", "endTime": "304.920s", "word": "работает", "confidence": 1}], "text": "Если не поможет позвонить уже завтра потому что сейчас техподдержка не работает", "confidence": 1}], "channelTag": "1"}, {"alternatives": [{"words": [{"startTime": "307.190s", "endTime": "307.850s", "word": "хорошо", "confidence": 1}, {"startTime": "307.950s", "endTime": "308.810s", "word": "ладно", "confidence": 1}], "text": "Хорошо ладно", "confidence": 1}], "channelTag": "1"}, {"alternatives": [{"words": [{"startTime": "309.930s", "endTime": "310.850s", "word": "спасибо", "confidence": 1}], "text": "Спасибо", "confidence": 1}], "channelTag": "1"}, {"alternatives": [{"words": [{"startTime": "310.880s", "endTime": "311.200s", "word": "спасибо", "confidence": 1}, {"startTime": "311.240s", "endTime": "311.320s", "word": "за", "confidence": 1}, {"startTime": "311.360s", "endTime": "312s", "word": "обращение", "confidence": 1}, {"startTime": "312.060s", "endTime": "312.140s", "word": "до", "confidence": 1}, {"startTime": "312.180s", "endTime": "313.040s", "word": "свидания", "confidence": 1}], "text": "Спасибо за обращение до свидания", "confidence": 1}], "channelTag": "1"}, {"alternatives": [{"words": [{"startTime": "313.350s", "endTime": "314.210s", "word": "угу", "confidence": 1}], "text": "Угу", "confidence": 1}], "channelTag": "1"}]